LICENSE
README.md
setup.py
pykeyboard/__init__.py
pykeyboard/inline_keyboard.py
pykeyboard/inline_pagination_keyboard.py
pykeyboard/reply_keyboard.py
pykeyboard.egg-info/PKG-INFO
pykeyboard.egg-info/SOURCES.txt
pykeyboard.egg-info/dependency_links.txt
pykeyboard.egg-info/requires.txt
pykeyboard.egg-info/top_level.txt