Metadata-Version: 2.1
Name: pykeyboard
Version: 0.1.5
Summary: Best Keyboard and Pagination for the Pyrogram Library.
Home-page: https://github.com/pystorage/pykeyboard
Author: PyMaster
Author-email: 
License: MIT
Keywords: telegram pyrogram keyboard bot userbot
Platform: UNKNOWN
Classifier: Programming Language :: Python
Classifier: Programming Language :: Python :: 3
Classifier: Programming Language :: Python :: 3.5
Classifier: Programming Language :: Python :: 3.6
Classifier: Programming Language :: Python :: 3.7
Classifier: Programming Language :: Python :: 3.8
Classifier: Programming Language :: Python :: 3.9
Classifier: Programming Language :: Python :: 3.10
Classifier: Topic :: Internet
Classifier: Topic :: Communications
Classifier: Topic :: Communications :: Chat
Classifier: Topic :: Software Development :: Libraries
Classifier: Topic :: Software Development :: Libraries :: Python Modules
License-File: LICENSE
